timecleaner.py
timeclean-0.1.dist-info/DESCRIPTION.rst
timeclean-0.1.dist-info/METADATA
timeclean-0.1.dist-info/RECORD
timeclean-0.1.dist-info/WHEEL
timeclean-0.1.dist-info/metadata.json
timeclean-0.1.dist-info/top_level.txt
