Metadata-Version: 2.0
Name: timeclean
Version: 0.1
Summary: Python package to help set up time series data for machine learning
Home-page: https://github.com/DineshRai/timecleaner
Author: Dinesh K Rai
Author-email: UNKNOWN
License: MIT
Platform: UNKNOWN
Requires-Dist: numpy
Requires-Dist: pandas
